baka_assets/__init__.py
baka_assets/assets.py
baka_assets-0.3.9.1.dist-info/DESCRIPTION.rst
baka_assets-0.3.9.1.dist-info/METADATA
baka_assets-0.3.9.1.dist-info/RECORD
baka_assets-0.3.9.1.dist-info/WHEEL
baka_assets-0.3.9.1.dist-info/metadata.json
baka_assets-0.3.9.1.dist-info/top_level.txt
example/__init__.py
example/__main__.py
