Metadata-Version: 2.0
Name: baka-assets
Version: 0.3.9.1
Summary: Assets for Baka and Pyramid
Home-page: https://github.com/baka-framework/baka_assets
Author: Nanang Suryadi
Author-email: nanang.jobs@gmail.com
License: MIT
Keywords: webpack,webassets,baka assets,pyramid assets
Platform: UNKNOWN
Classifier: Development Status :: 5 - Production/Stable
Classifier: Intended Audience :: Developers
Classifier: License :: OSI Approved :: MIT License
Classifier: Programming Language :: Python :: 2.7
Classifier: Programming Language :: Python :: 3.3
Classifier: Programming Language :: Python :: 3.4
Classifier: Programming Language :: Python :: 3.5
Classifier: Programming Language :: Python :: 3.6
Requires-Dist: PyExecJS
Requires-Dist: PyYAML
Requires-Dist: cssmin
Requires-Dist: jsmin
Requires-Dist: plim
Requires-Dist: pyScss
Requires-Dist: pyramid
Requires-Dist: six
Requires-Dist: webassets
